py_youtube/__init__.py
py_youtube/pyyoutube.py
py_youtube/search_video.py
py_youtube-1.1.7.dist-info/LICENSE
py_youtube-1.1.7.dist-info/METADATA
py_youtube-1.1.7.dist-info/WHEEL
py_youtube-1.1.7.dist-info/top_level.txt
py_youtube-1.1.7.dist-info/RECORD
