Metadata-Version: 2.1
Name: py-youtube
Version: 1.1.7
Summary: Python library Get YouTube Video Data & Search Video
Home-page: https://github.com/lntechnical2/PyYouTube
Author: mrlokaman
Author-email: ln0technical@gmail.com
License: MIT
Platform: UNKNOWN
Classifier: Programming Language :: Python :: 3
Classifier: License :: OSI Approved :: MIT License
Classifier: Operating System :: OS Independent
Requires-Python: >=3.6
